bandsintown/__init__.py
bandsintown/client.py
python_bandsintown-1.0.0.dist-info/DESCRIPTION.rst
python_bandsintown-1.0.0.dist-info/METADATA
python_bandsintown-1.0.0.dist-info/RECORD
python_bandsintown-1.0.0.dist-info/WHEEL
python_bandsintown-1.0.0.dist-info/metadata.json
python_bandsintown-1.0.0.dist-info/top_level.txt
tests/__init__.py
tests/test_client.py
