Metadata-Version: 2.0
Name: python-bandsintown
Version: 1.0.0
Summary: Simple Python client for the Bandsintown API
Home-page: https://github.com/chrisforrette/python-bandsintown
Author: Chris Forrette
Author-email: chris@chrisforrette.com
License: MIT
Keywords: bandsintown api client tour dates
Platform: UNKNOWN
Classifier: Intended Audience :: Developers
Classifier: Operating System :: OS Independent
Classifier: Topic :: Software Development
Classifier: Programming Language :: Python :: 2.7
Classifier: Programming Language :: Python :: 3.4
Requires-Dist: requests (<3)
